setup.py
djcolour/__init__.py
djcolour/base.py
djcolour/fields.py
djcolour/tests.py
djcolour.egg-info/PKG-INFO
djcolour.egg-info/SOURCES.txt
djcolour.egg-info/dependency_links.txt
djcolour.egg-info/requires.txt
djcolour.egg-info/top_level.txt
djcolour/forms/__init__.py
djcolour/forms/fields.py