Metadata-Version: 1.1
Name: djcolour
Version: 0.2.2
Summary: Automatically use `colour.Color` in Python, `django.db.models.CharField` on the database, and `<input type="color">` on the forms.
Home-page: https://github.com/jansegre/djcolour
Author: Jan Segre
Author-email: jan@segre.in
License: MIT
Platform: UNKNOWN
Classifier: Development Status :: 4 - Beta
Classifier: Environment :: Web Environment
Classifier: Framework :: Django :: 1.11
Classifier: Framework :: Django
Classifier: Intended Audience :: Developers
Classifier: License :: OSI Approved :: MIT License
Classifier: Operating System :: OS Independent
Classifier: Programming Language :: Python :: 3 :: Only
Classifier: Programming Language :: Python :: 3.4
Classifier: Programming Language :: Python :: 3.5
